setup.py
python_sample_app/__init__.py
python_sample_app/main.py
python_sample_app.egg-info/PKG-INFO
python_sample_app.egg-info/SOURCES.txt
python_sample_app.egg-info/dependency_links.txt
python_sample_app.egg-info/entry_points.txt
python_sample_app.egg-info/top_level.txt