Metadata-Version: 1.0
Name: python-sample-app
Version: 1.0
Summary: UNKNOWN
Home-page: https://github.com/becosta/python-sample-app
Author: Benjamin Costa
Author-email: benjamin.costa.75@gmail.com
License: MIT
Platform: UNKNOWN
